{
    "DNDConfig": null,
    "_height_": {
        "type": "string",
        "value": "65dp"
    },
    "_margin_": [
        0,
        0,
        0,
        0
    ],
    "_orientation_": 6,
    "_padding_": [
        0,
        0,
        0,
        0
    ],
    "_percent_": true,
    "_skin_": "sf763122309040d2878e39236d63bb50",
    "allboxes": [],
    "autogrowmode": 0,
    "canUpdateUI": true,
    "children": [
        "flxcDriveContainer",
        "flxcDelete"
    ],
    "clipbounds": true,
    "containerId": true,
    "containerweight": 100,
    "enablescrolling": true,
    "id": "flxOne",
    "info": null,
    "isTemplate": true,
    "isvisible": true,
    "kuid": "ba58056bba594fb6b5016db3ab09a346",
    "layouttype": 2,
    "name": "kony.ui.FlexContainer",
    "parent": "tmpDrive",
    "pf": "tmpDrive",
    "snapgridsize": 10,
    "snaptogrid": true,
    "wType": "FlexContainer",
    "widgetalignment": 1
}